heliodash/__init__.py
heliodash/jupiter/__init__.py
heliodash/jupiter/juno/__init__.py
heliodash/jupiter/juno/juno_jiram_image.py
heliodash/jupiter/juno/pds_parser.py
heliodash/sun/__init__.py
heliodash/sun/goes/__init__.py
heliodash/sun/goes/goes_proton_flux.py
heliodash/sun/goes/goes_suvi.py
heliodash/sun/goes/goes_xray_flux.py
heliodash/sun/hinode/__init__.py
heliodash/sun/hinode/hinode_image.py
heliodash/sun/proba2/__init__.py
heliodash/sun/proba2/proba2_image.py
heliodash/sun/psp/__init__.py
heliodash/sun/psp/psp_image.py
heliodash/sun/sdo/__init__.py
heliodash/sun/sdo/sdo_image.py
heliodash/sun/sdo/sdo_video.py
heliodash/sun/soho/__init__.py
heliodash/sun/soho/soho_image.py
heliodash/sun/soho/soho_video.py
heliodash/sun/stereo/__init__.py
heliodash/sun/stereo/stereo_image.py
heliodash/sun/stereo/stereo_video.py
heliodash/system/__init__.py
heliodash/system/body_position.py
heliodash/system/body_position_plotly.py
heliodash/util/__init__.py
heliodash/util/html_parser.py
heliodash/util/html_video.py
heliodash-0.0.17.dist-info/licenses/LICENSE
heliodash-0.0.17.dist-info/METADATA
heliodash-0.0.17.dist-info/WHEEL
heliodash-0.0.17.dist-info/top_level.txt
heliodash-0.0.17.dist-info/RECORD
